llmserve/__init__.py
llmserve/api/__init__.py
llmserve/api/cli.py
llmserve/api/env.py
llmserve/api/sdk.py
llmserve/backend/__init__.py
llmserve/backend/logger.py
llmserve/backend/llm/__init__.py
llmserve/backend/llm/predictor.py
llmserve/backend/llm/utils.py
llmserve/backend/llm/ft/__init__.py
llmserve/backend/llm/ft/_base.py
llmserve/backend/llm/ft/callback.py
llmserve/backend/llm/ft/const.py
llmserve/backend/llm/ft/transformer.py
llmserve/backend/llm/ft/utils.py
llmserve/backend/llm/ft/tasks/__init__.py
llmserve/backend/llm/ft/tasks/_base.py
llmserve/backend/llm/ft/tasks/maskedlm_imdb.py
llmserve/backend/llm/ft/tasks/noheader_shibing624_AdvertiseGen.py
llmserve/backend/llm/ft/tasks/sequenceclassification_glue_cola.py
llmserve/backend/llm/ft/tasks/sequenceclassification_glue_mrpc.py
llmserve/backend/llm/ft/tasks/sequenceclassification_yelp_review_full.py
llmserve/backend/llm/ft/tasks/tokenclassification_conll2003.py
llmserve/backend/llm/initializers/__init__.py
llmserve/backend/llm/initializers/_base.py
llmserve/backend/llm/initializers/llamacpp.py
llmserve/backend/llm/initializers/models.py
llmserve/backend/llm/initializers/vllm.py
llmserve/backend/llm/initializers/hf_transformers/__init__.py
llmserve/backend/llm/initializers/hf_transformers/base.py
llmserve/backend/llm/initializers/hf_transformers/deepspeed.py
llmserve/backend/llm/pipelines/__init__.py
llmserve/backend/llm/pipelines/_base.py
llmserve/backend/llm/pipelines/default_pipeline.py
llmserve/backend/llm/pipelines/default_transformers_pipeline.py
llmserve/backend/llm/pipelines/processors.py
llmserve/backend/llm/pipelines/utils.py
llmserve/backend/llm/pipelines/llamacpp/__init__.py
llmserve/backend/llm/pipelines/llamacpp/llamacpp_pipeline.py
llmserve/backend/llm/pipelines/llamacpp/processors.py
llmserve/backend/llm/pipelines/vllm/__init__.py
llmserve/backend/llm/pipelines/vllm/error_handling.py
llmserve/backend/llm/pipelines/vllm/generation.py
llmserve/backend/llm/pipelines/vllm/models.py
llm_serve-0.0.1.dist-info/LICENSE
llm_serve-0.0.1.dist-info/METADATA
llm_serve-0.0.1.dist-info/WHEEL
llm_serve-0.0.1.dist-info/dependency_links.txt
llm_serve-0.0.1.dist-info/entry_points.txt
llm_serve-0.0.1.dist-info/top_level.txt
llm_serve-0.0.1.dist-info/RECORD
